{
  "js":{
    "1":"对不起,用户名已经被使用",
    "2":"用户名必须填写",
    "3":"用户名长度为2-10位",
    "4":"密码必须填写",
    "5":"密码长度为6-12位",
    "6":"请输入确认密码",
    "7":"两次密码必须相同",
    "8":"请选择国家",
    "9":"请输入邮箱",
    "10":"请输入正确的邮箱",
    "12":"介绍人最少2个字符",
    "13":"介绍人最多50个字符",
    "14":"验证码不能为空",
    "15":"验证码错误",
    "16":"请输入4位验证码",
    "17":"请输入4位验证码",
    "18":"姓不能为空",
    "19":"最少1位",
    "20":"最多6位",
    "21":"名不能为空",
    "22":"最少2位",
    "23":"最多20位",
    "24":"昵称不能为空",
    "25":"最少2位",
    "26":"最多30位",
    "27":"英文姓名不能为空",
    "28":"最少2位",
    "29":"最多30位",
    "30":"生日不能为空",
    "31":"QQ不能为空",
    "32":"取款密码不能为空",
    "33":"最多16位",
    "34":"手机不能为空",
    "35":"证件类型不能为空",
    "36":"证件不能为空",
    "37":"请确认接受网站条款"
  },
  "country_name":{
    "Australia":"澳大利亚",
    "Brunei":"文莱",
    "Cambodia":"柬埔寨",
    "Canada":"加拿大",
    "China":"中国",
    "EU":"欧盟",
    "India":"印度",
    "Indonesia":"印度尼西亚",
    "Japan":"日本",
    "Korea":"韩国",
    "Laos":"老挝",
    "Malaysia":"马来西亚",
    "Myanmar":"缅甸",
    "New Zealand":"新西兰",
    "Philippines":"菲律宾",
    "Russia":"俄罗斯",
    "Singapore":"新加坡",
    "Thailand":"泰国",
    "United States":"美国",
    "Vietnam":"越南"
  },
  "certificate_type":{
    "ID number":"身份证",
    "Driver license":"驾驶证",
    "Military officer":"军官证",
    "Passport":"护照"
  },
  "sex":{
    "male":"男",
    "female":"女"
  },
  "custCode":{
    "filed":"custCode",
    "name":"用户名：",
    "help":"用户名由6~12位小写英文a~z或数字组成"
  },
  "passwd":{
    "filed":"passwd",
    "name":"设置密码：",
    "help":"密码长度6～20位a-z,0-9,只允许以下特殊字符@*_-.,;&"
  },
  "repasswd":{
    "filed":"repasswd",
    "name":"确认密码：",
    "help":"再次输入密码"
  },
  "country":{
    "filed":"country",
    "name":"国家："
  },
  "affiliateId":{
    "filed":"affiliateId",
    "name":"介绍人："
  },
  "firstName":{
    "filed":"firstName",
    "name":"姓："
  },
  "lastName":{
    "filed":"lastName",
    "name":"名："
  },
  "nickName":{
    "filed":"nickName",
    "name":"昵称："
  },
  "enName":{
    "filed":"enName",
    "name":"英文姓名："
  },
  "birthDate":{
    "filed":"birthDate",
    "name":"生日："
  },
  "certificateType":{
    "filed":"certificateType",
    "name":"证件类型："
  },
  "certificate":{
    "filed":"certificate",
    "name":"证件："
  },
  "custGender":{
    "filed":"custGender",
    "name":"性别："
  },
  "mobileNumber":{
    "filed":"mobileNumber",
    "name":"手机："
  },
  "drawPwd":{
    "filed":"drawPwd",
    "name":"取款密码："
  },
  "qq":{
    "filed":"qq",
    "name":"QQ："
  },
  "validateCode":{
    "filed":"validateCode",
    "name":"验证码："
  },
  "emailAddress":{
    "filed":"emailAddress",
    "name":"邮箱："
  },
  "reg-header-title":"新用户注册",
  "reg-header-text":"如您已有帐户，立刻在此  <a href='/login'>登录</a>",
  "reg-text":"注册时有任何问题，请联系我们24小时协助解决<a href='/service'>在线客服</a><br>本网站采用Global Trust最先进的128/256 bit SSL服务器加密机制",
  "ck1":"我确认已年满18岁，并已阅读和接受本网站政策、隐私声明、条款和条件。",
  "reg-btn":"马上注册"
}